__init__.py
regex_dictionary.py
test_regex_dictionary.py
regex_dictionary-1.0.2.dist-info/LICENSE
regex_dictionary-1.0.2.dist-info/METADATA
regex_dictionary-1.0.2.dist-info/WHEEL
regex_dictionary-1.0.2.dist-info/top_level.txt
regex_dictionary-1.0.2.dist-info/RECORD
