Metadata-Version: 2.1
Name: regex-dictionary
Version: 1.0.2
Summary: Simple type that extends default python dict to dict with regex keys
Author-email: Alex Makhonin <makhonin.a.ru@gmail.com>
License: Apache License
Project-URL: Homepage, https://github.com/alex123012/regex-dictionary
Keywords: dict,regex,regexdict,dictregex,regex-dictionary,dictionary,regex-dict
Classifier: License :: OSI Approved :: Apache Software License
Classifier: Programming Language :: Python
Classifier: Programming Language :: Python :: 3
Requires-Python: >=3.9
License-File: LICENSE
Provides-Extra: dev
Requires-Dist: pip-tools ; extra == 'dev'
